ms_outlook_calendar_utils/.env.example
ms_outlook_calendar_utils/__init__.py
ms_outlook_calendar_utils/clone_calendar_events.py
ms_outlook_calendar_utils/get_calendar_events.py
ms_outlook_calendar_utils/reserve_time.py
ms_outlook_calendar_utils-0.2.0.dist-info/AUTHORS.rst
ms_outlook_calendar_utils-0.2.0.dist-info/LICENSE
ms_outlook_calendar_utils-0.2.0.dist-info/METADATA
ms_outlook_calendar_utils-0.2.0.dist-info/WHEEL
ms_outlook_calendar_utils-0.2.0.dist-info/entry_points.txt
ms_outlook_calendar_utils-0.2.0.dist-info/top_level.txt
ms_outlook_calendar_utils-0.2.0.dist-info/RECORD
