Metadata-Version: 2.1
Name: ms_outlook_calendar_utils
Version: 0.2.0
Summary: Collection of Python utility scripts for manipulating MS Outlook Calendar events.
Home-page: https://github.com/jai-python3/ms_outlook_calendar_utils
Author: Jaideep Sundaram
Author-email: jai.python3@gmail.com
Keywords: ms_outlook_calendar_utils
Classifier: Development Status :: 2 - Pre-Alpha
Classifier: Intended Audience :: Developers
Classifier: Natural Language :: English
Classifier: Programming Language :: Python :: 3
Classifier: Programming Language :: Python :: 3.6
Classifier: Programming Language :: Python :: 3.7
Classifier: Programming Language :: Python :: 3.8
Requires-Python: >=3.6
License-File: LICENSE
License-File: AUTHORS.rst
Requires-Dist: Click >=7.0
Requires-Dist: pywin32
Requires-Dist: python-dotenv
